canto_safe_cli/__init__.py
canto_safe_cli/ethereum_hd_wallet.py
canto_safe_cli/main.py
canto_safe_cli/prompt_parser.py
canto_safe_cli/safe_addresses.py
canto_safe_cli/safe_completer.py
canto_safe_cli/safe_completer_constants.py
canto_safe_cli/safe_creator.py
canto_safe_cli/safe_lexer.py
canto_safe_cli/utils.py
canto_safe_cli/version.py
canto_safe_cli/api/__init__.py
canto_safe_cli/api/base_api.py
canto_safe_cli/api/etherscan_api.py
canto_safe_cli/api/relay_service_api.py
canto_safe_cli/api/transaction_service_api.py
canto_safe_cli/operators/__init__.py
canto_safe_cli/operators/safe_operator.py
canto_safe_cli/operators/safe_relay_operator.py
canto_safe_cli/operators/safe_tx_service_operator.py
tests/__init__.py
tests/safe_cli_test_case_mixin.py
tests/test_ethereum_hd_wallet.py
tests/test_safe_cli.py
tests/test_safe_operator.py
tests/utils.py
tests/api/__init__.py
tests/api/test_gnosis_transaction.py
canto_safe_cli-0.5.2.dist-info/LICENSE
canto_safe_cli-0.5.2.dist-info/METADATA
canto_safe_cli-0.5.2.dist-info/WHEEL
canto_safe_cli-0.5.2.dist-info/entry_points.txt
canto_safe_cli-0.5.2.dist-info/top_level.txt
canto_safe_cli-0.5.2.dist-info/RECORD
