Metadata-Version: 2.1
Name: canto-safe-cli
Version: 0.5.2
Summary: Command Line Interface for Gnosis Safe
Home-page: https://github.com/neobase-one/safe-cli
Download-URL: https://github.com/neobase-one/safe-cli/releases
Author: Uxío Fuentefría
Author-email: uxio@gnosis.io
License: MIT
Classifier: Programming Language :: Python :: 3
Classifier: License :: OSI Approved :: MIT License
Classifier: Operating System :: OS Independent
Requires-Python: >=3.6
License-File: LICENSE
Requires-Dist: colorama (>=0.4)
Requires-Dist: prompt-toolkit (>=3)
Requires-Dist: pyfiglet (>=0.8)
Requires-Dist: pygments (>=2)
Requires-Dist: requests (>=2)
Requires-Dist: safe-eth-py (>=4.5.2)
Requires-Dist: tabulate (>=0.8)
Requires-Dist: cached-property (==1.5.2) ; python_version < "3.8"
Requires-Dist: typing-extensions (>3<4) ; python_version < "3.8"
